Metadata-Version: 1.2
Name: ADLoginValidation
Version: 0.2
Summary: UNKNOWN
Home-page: https://gitlab.com/ibichara/adloginvalidation
Author: Igor Bichara
Author-email: igorbacoutinho@gmail.com
License: MIT
Keywords: microsoft adfs login token validation
Platform: UNKNOWN
Requires-Python: >=3
